agentjson-0.1.2.dist-info/METADATA
agentjson-0.1.2.dist-info/WHEEL
agentjson-0.1.2.dist-info/entry_points.txt
agentjson/__init__.py
agentjson/agentjson_rust.abi3.so
agentjson-0.1.2.dist-info/RECORD
