Metadata-Version: 2.4
Name: agentjson
Version: 0.1.2
Classifier: Development Status :: 4 - Beta
Classifier: Intended Audience :: Developers
Classifier: License :: OSI Approved :: MIT License
Classifier: License :: OSI Approved :: Apache Software License
Classifier: Programming Language :: Python :: 3
Classifier: Programming Language :: Python :: 3.9
Classifier: Programming Language :: Python :: 3.10
Classifier: Programming Language :: Python :: 3.11
Classifier: Programming Language :: Python :: 3.12
Classifier: Programming Language :: Python :: 3.13
Classifier: Programming Language :: Rust
Classifier: Topic :: Software Development :: Libraries :: Python Modules
Classifier: Topic :: Text Processing :: General
Classifier: Topic :: Internet :: WWW/HTTP :: Dynamic Content
Requires-Dist: anthropic ; extra == 'anthropic'
Provides-Extra: anthropic
Summary: Probabilistic JSON repair library powered by Rust - fixes broken JSON from LLMs
Keywords: json,parser,repair,llm,probabilistic,beam-search,orjson
Author: agentjson contributors
License: MIT OR Apache-2.0
Requires-Python: >=3.9
Project-URL: Homepage, https://github.com/sionic-ai/agentjson
Project-URL: Repository, https://github.com/sionic-ai/agentjson
Project-URL: Documentation, https://github.com/sionic-ai/agentjson#readme
